agreement/__init__.py
agreement/metrics.py
agreement/utils/__init__.py
agreement/utils/kernels.py
agreement/utils/transform.py
agreement-0.1.1.dist-info/LICENSE
agreement-0.1.1.dist-info/METADATA
agreement-0.1.1.dist-info/WHEEL
agreement-0.1.1.dist-info/top_level.txt
agreement-0.1.1.dist-info/RECORD
