Metadata-Version: 2.1
Name: agreement
Version: 0.1.1
Summary: An implementation of popular agreement coefficients used for categorical measurements.
Home-page: https://github.com/heolin123/agreement
Author: Wojciech Włodarczyk
Author-email: wlodarczyk.woj@example.com
License: UNKNOWN
Project-URL: Bug Tracker, https://github.com/heolin123/agreement/issues
Platform: UNKNOWN
Classifier: Programming Language :: Python :: 3
Classifier: License :: OSI Approved :: GNU General Public License v3 or later (GPLv3+)
Classifier: Operating System :: OS Independent
Requires-Python: >=3.6
License-File: LICENSE
Requires-Dist: numpy (>=1.20.2)
